{"cameraMode":{"drawMode":0,"name":"Shaded","section":"Shading Mode"},"sceneLighting":true,"audioPlay":false,"sceneViewState":{"m_AlwaysRefresh":false,"showFog":true,"showSkybox":true,"showFlares":true,"showImageEffects":true,"showParticleSystems":true,"showVisualEffectGraphs":true,"m_FxEnabled":true},"in2DMode":false,"pivot":{"x":-8.482684135437012,"y":-7.266735076904297,"z":-8.55164623260498},"rotation":{"x":-0.12698587775230409,"y":0.8660341501235962,"z":-0.2652598023414612,"w":-0.40583091974258425},"size":14.140215873718262,"orthographic":false}